bimp/__init__.py
bimp/bimp.py
bimp-1.8.dist-info/LICENSE
bimp-1.8.dist-info/METADATA
bimp-1.8.dist-info/WHEEL
bimp-1.8.dist-info/top_level.txt
bimp-1.8.dist-info/RECORD
