Metadata-Version: 2.1
Name: bimp
Version: 1.8
Summary: Make-life-easier Python functions for image processing.
Home-page: https://github.com/JankoSmejkal/bimp/blob/master/README.md
Author: Jan Smejkal
Author-email: jankosmejkal@yahoo.com
License: UNKNOWN
Platform: UNKNOWN
Classifier: Programming Language :: Python :: 3
Classifier: License :: OSI Approved :: MIT License
Classifier: Operating System :: OS Independent
Requires-Python: >=3.6
